{
  "title": "Future Features Set to Transform User Experience",
  "date": "2026-04-07T22:00:00.000Z",
  "type": "nightly",
  "topics": [
    {
      "title": "Refactoring and Code Improvements",
      "summary": "Several pull requests focused on refactoring code, including the use of new settings in pnpm and the implementation of a composable for the vulnerability tree. These changes aim to enhance code maintainability and performance.",
      "relevanceScore": 9,
      "sources": [
        {
          "platform": "github",
          "url": "https://github.com/npmx-dev/npmx.dev/pull/2407"
        },
        {
          "platform": "github",
          "url": "https://github.com/npmx-dev/npmx.dev/pull/2405"
        }
      ]
    },
    {
      "title": "Community Engagement and Announcements",
      "summary": "The npmx community is actively engaging through various platforms, with announcements about new episodes of Igalia Chats discussing the project and its community. This highlights the ongoing dialogue and collaboration within the open-source ecosystem.",
      "relevanceScore": 9,
      "sources": [
        {
          "platform": "bluesky",
          "url": "https://bsky.app/profile/igalia.com/post/3miwbkgbgyk2m"
        },
        {
          "platform": "bluesky",
          "url": "https://bsky.app/profile/danielroe.dev/post/3miwhixzfps2n"
        }
      ]
    },
    {
      "title": "Documentation Updates",
      "summary": "Recent changes include updates to the README to reflect npmjs.com's new dark mode and the addition of links to socket.dev. These enhancements aim to improve user experience and provide clearer information about the project.",
      "relevanceScore": 8,
      "sources": [
        {
          "platform": "github",
          "url": "https://github.com/npmx-dev/npmx.dev/pull/2409"
        },
        {
          "platform": "github",
          "url": "https://github.com/npmx-dev/npmx.dev/pull/2370"
        }
      ]
    },
    {
      "title": "Issue Resolutions",
      "summary": "Several issues have been closed, including updates related to dark mode and the addition of socket.dev links. These resolutions indicate active project management and responsiveness to community feedback.",
      "relevanceScore": 8,
      "sources": [
        {
          "platform": "github",
          "url": "https://github.com/npmx-dev/npmx.dev/issues/2408"
        },
        {
          "platform": "github",
          "url": "https://github.com/npmx-dev/npmx.dev/issues/2369"
        }
      ]
    },
    {
      "title": "Upcoming Features and Enhancements",
      "summary": "Exciting developments are on the horizon, including module replacements v3, which aims to enhance messaging and data representation in npmx. This indicates a focus on improving user experience and functionality.",
      "relevanceScore": 8,
      "sources": [
        {
          "platform": "bluesky",
          "url": "https://bsky.app/profile/43081j.com/post/3mivw5m7nls2n"
        }
      ]
    },
    {
      "title": "Internationalization Efforts",
      "summary": "Updates to Simplified and Traditional Chinese translations have been made to improve accessibility for non-English speaking users. This effort reflects the project's commitment to inclusivity and global reach.",
      "relevanceScore": 7,
      "sources": [
        {
          "platform": "github",
          "url": "https://github.com/npmx-dev/npmx.dev/pull/2404"
        }
      ]
    }
  ]
}