{
  "title": "tinyglobby Surpasses Rivals in Package Evolution",
  "date": "2026-06-07T14:00:00.000Z",
  "type": "midday",
  "topics": [
    {
      "title": "Package Evolution",
      "summary": "The tinyglobby package has surpassed both globby and fast-glob after two years of development. This milestone highlights the growth and impact of tinyglobby in the ecosystem, showcasing the collaborative efforts of developers like @e18e.dev and others who contributed to its success.",
      "relevanceScore": 9,
      "sources": [
        {
          "platform": "bluesky",
          "url": "https://bsky.app/profile/superchupu.dev/post/3mnow4mnkzs2w"
        }
      ]
    }
  ]
}