{
  "title": "Community Spirit Shines in Recent Contributions",
  "date": "2026-03-26T06:00:00.000Z",
  "type": "daily",
  "topics": [
    {
      "title": "Community Contributions",
      "summary": "Recent contributions to the npmx project have been highlighted, showcasing the excitement and nervousness of developers. One contributor expressed joy over making a visible contribution, allowing users to download package tarballs. This reflects the collaborative spirit within the community.",
      "relevanceScore": 9,
      "sources": [
        {
          "platform": "bluesky",
          "url": "https://bsky.app/profile/lopeadebesin.bsky.social/post/3mhw5ep3ovc2f"
        }
      ]
    },
    {
      "title": "Developer Engagement",
      "summary": "Developers are actively engaging with the npmx project, sharing their experiences and contributions on social platforms. The excitement of contributing to open-source projects is evident, fostering a sense of community and collaboration among developers.",
      "relevanceScore": 8,
      "sources": [
        {
          "platform": "bluesky",
          "url": "https://bsky.app/profile/erus.dev/post/3mhvo3ibugk2j"
        }
      ]
    }
  ]
}